LICENSE.txt
README.md
setup.py
DataCleaner_rr/__init__.py
DataCleaner_rr/categorical_encoder.py
DataCleaner_rr/data_type_converter.py
DataCleaner_rr/datetime_handler.py
DataCleaner_rr/missing_value_handler.py
DataCleaner_rr/outlier_handler.py
DataCleaner_rr/scaler.py
DataCleaner_rr/text_cleaner.py
DataCleaner_rr.egg-info/PKG-INFO
DataCleaner_rr.egg-info/SOURCES.txt
DataCleaner_rr.egg-info/dependency_links.txt
DataCleaner_rr.egg-info/requires.txt
DataCleaner_rr.egg-info/top_level.txt
Test/__init__.py
Test/mainn.py
Test/test.py
Test/test_categorical_encoder.py
Test/test_data_type_converter.py
Test/test_datetime_handler.py
Test/test_missing_value_handler.py
Test/test_outlier_handler.py
Test/test_scaler.py
Test/test_text_cleaner.py
test/test.py
test/test_categorical_encoder.py
test/test_data_type_converter.py
test/test_datetime_handler.py
test/test_missing_value_handler.py
test/test_outlier_handler.py
test/test_scaler.py
test/test_text_cleaner.py