Metadata-Version: 2.1
Name: DataCleaner-rr
Version: 0.1.0
Summary: A comprehensive data preprocessing library for data cleaning, transformation, and manipulation
Author: Rana Güngör
Author-email: rana.gungor@stu.fsm.edu.tr
Classifier: Programming Language :: Python :: 3
Classifier: License :: OSI Approved :: MIT License
Classifier: Operating System :: OS Independent
Requires-Python: >=3.6
License-File: LICENSE.txt
